dbt/adapters/devnull/__init__.py
dbt/adapters/devnull/__version__.py
dbt/adapters/devnull/connections.py
dbt/adapters/devnull/impl.py
dbt/include/devnull/__init__.py
dbt/include/devnull/dbt_project.yml
dbt/include/devnull/sample_profiles.yml
dbt/include/devnull/macros/catalog.sql
dbt_devnull-1.1.3.dist-info/LICENSE
dbt_devnull-1.1.3.dist-info/METADATA
dbt_devnull-1.1.3.dist-info/WHEEL
dbt_devnull-1.1.3.dist-info/top_level.txt
dbt_devnull-1.1.3.dist-info/RECORD
