Metadata-Version: 2.1
Name: dbt-devnull
Version: 1.1.3
Summary: The devnull adapter plugin for dbt
Home-page: https://github.com/bachng2017/dbt-devnull
Author: bachng
Author-email: bachng@gmail.com
License: Apache
Platform: UNKNOWN
License-File: LICENSE
Requires-Dist: dbt-core (>=1.1.0)
